Workbook

Sheet Test Cases
A1: ID | B1: Modul | C1: Skenario | D1: Langkah Pengujian | E1: Hasil yang Diharapkan | F1: Prioritas | G1: Status | H1: Penguji | I1: Tanggal Uji | J1: Hasil Aktual / Catatan
A2: FR-01 | B2: Financial Report | C2: Cetak Owners Statement dasar | D2: Pastikan ada invoice/bill posted ber-link properti. Jalankan wizard Owners Statement untuk periode berjalan. | E2: PDF tampil dengan 9 section; angka Income/Expense terisi dari GL. | F2: High | G2: Not Run
A3: FR-02 | B3: Financial Report | C3: Actual vs Budget | D3: Buat Property Budget per akun untuk bulan uji. Cetak ulang Owners Statement. | E3: Kolom Budget & Variance & %Var pada I&E dan Performance Summary terisi. | F3: High | G3: Not Run
A4: FR-03 | B4: Financial Report | C4: Multi-owner & remittance | D4: Isi 2 owner (60/40). Owner Remittance → Compute from Owners → Post. | E4: Alokasi 60/40; jurnal Dr Remittance/Cr Trust terbuat; Less Remittances muncul. | F4: High | G4: Not Run
A5: FR-04 | B5: Financial Report | C5: Trust roll-forward | D5: Set Trust Bank Account; ada penerimaan & pembayaran ter-rekonsiliasi. | E5: Opening + Net Cash − Remittances = Closing Trust Balance konsisten. | F5: Medium | G5: Not Run
A6: FR-05 | B6: Financial Report | C6: Security Deposit liability | D6: Buat Security Deposit → Mark as Held; tambah baris refund; Post Deductions/Refunds. | E6: Balance berkurang; kolom Sec Dep Bal di Tenant Balances terisi. | F6: Medium | G6: Not Run
A7: FR-06 | B7: Financial Report | C7: Integrasi Analytic | D7: Set analytic account properti. Posting invoice ber-link properti. Buka 'Analytic Items'. | E7: Baris income/expense punya analytic_distribution; muncul di Analytic Items. | F7: Medium | G7: Not Run
A8: FR-07 | B8: Financial Report | C8: Aged Arrears | D8: Biarkan beberapa invoice jatuh tempo umur berbeda. Cetak laporan. | E8: Tunggakan terbagi ke bucket Current/1/2/3/4+ bulan dengan total benar. | F8: Medium | G8: Not Run
A9: GT-01 | B9: GTO & Meter | C9: GTO Higher-of | D9: Kontrak GTO higher_of, %=5, base=10jt, turnover=300jt. Compute. | E9: percentage_rent=15jt; billable=5jt; invoice 5jt. | F9: High | G9: Not Run
A10: GT-02 | B10: GTO & Meter | C10: GTO Base+Overage | D10: base_plus, %=5, breakpoint=200jt, turnover=300jt. | E10: billable=(300−200)jt×5%=5jt. | F10: Medium | G10: Not Run
A11: GT-03 | B11: GTO & Meter | C11: GTO Pure % | D11: pure, %=8, turnover=100jt. | E11: billable=8jt. | F11: Low | G11: Not Run
A12: MT-01 | B12: GTO & Meter | C12: Meter reading & recharge | D12: Tarif=1.500/kWh, previous=100, current=350. Create Recharge Invoice. | E12: consumption=250; amount=375.000; invoice qty 250×1.500. | F12: High | G12: Not Run
A13: MT-02 | B13: GTO & Meter | C13: Previous reading otomatis | D13: Buat reading kedua pada meter sama. | E13: previous_reading terisi otomatis dari current terakhir. | F13: Medium | G13: Not Run
... A80: E2E-5 | B80: End-to-End | C80: Move-out | D80: Handover Move-out + make-good; Security Deposit refund; kontrak ditutup. | E80: Deposit terselesaikan; Sec Dep Bal nol; kontrak closed. | F80: Medium | G80: Not Run

Sheet Summary
A1: UAT SUMMARY
A3: Total Test Cases | B3: =COUNTA('Test Cases'!A2:A80)
A4: Pass | B4: =COUNTIF('Test Cases'!G2:G80,"Pass")
A5: Fail | B5: =COUNTIF('Test Cases'!G2:G80,"Fail")
A6: Blocked | B6: =COUNTIF('Test Cases'!G2:G80,"Blocked")
A7: N/A | B7: =COUNTIF('Test Cases'!G2:G80,"N/A")
A8: Not Run | B8: =COUNTIF('Test Cases'!G2:G80,"Not Run")
A9: % Pass | B9: =IF(B3+B4=0,0,B3/(B3+B4))
A11: Per Modul
A12: Modul | B12: Total | C12: Pass | D12: Fail | E12: Not Run
A13: Financial Report | B13: =COUNTIF('Test Cases'!B2:B80,A13) | C13: =COUNTIFS('Test Cases'!B2:B80,A13,'Test Cases'!G2:G80,"Pass") | D13: =COUNTIFS('Test Cases'!B2:B80,A13,'Test Cases'!G2:G80,"Fail") | E13: =COUNTIFS('Test Cases'!B2:B80,A13,'Test Cases'!G2:G80,"Not Run")
A14: GTO & Meter | B14: =COUNTIF('Test Cases'!B2:B80,A14) | C14: =COUNTIFS('Test Cases'!B2:B80,A14,'Test Cases'!G2:G80,"Pass") | D14: =COUNTIFS('Test Cases'!B2:B80,A14,'Test Cases'!G2:G80,"Fail") | E14: =COUNTIFS('Test Cases'!B2:B80,A14,'Test Cases'!G2:G80,"Not Run")
A15: Guarantee | B15: =COUNTIF('Test Cases'!B2:B80,A15) | C15: =COUNTIFS('Test Cases'!B2:B80,A15,'Test Cases'!G2:G80,"Pass") | D15: =COUNTIFS('Test Cases'!B2:B80,A15,'Test Cases'!G2:G80,"Fail") | E15: =COUNTIFS('Test Cases'!B2:B80,A15,'Test Cases'!G2:G80,"Not Run")
A16: Casual Leasing | B16: =COUNTIF('Test Cases'!B2:B80,A16) | C16: =COUNTIFS('Test Cases'!B2:B80,A16,'Test Cases'!G2:G80,"Pass") | D16: =COUNTIFS('Test Cases'!B2:B80,A16,'Test Cases'!G2:G80,"Fail") | E16: =COUNTIFS('Test Cases'!B2:B80,A16,'Test Cases'!G2:G80,"Not Run")
A17: Handover | B17: =COUNTIF('Test Cases'!B2:B80,A17) | C17: =COUNTIFS('Test Cases'!B2:B80,A17,'Test Cases'!G2:G80,"Pass") | D17: =COUNTIFS('Test Cases'!B2:B80,A17,'Test Cases'!G2:G80,"Fail") | E17: =COUNTIFS('Test Cases'!B2:B80,A17,'Test Cases'!G2:G80,"Not Run")
A18: Tenant Portal | B18: =COUNTIF('Test Cases'!B2:B80,A18) | C18: =COUNTIFS('Test Cases'!B2:B80,A18,'Test Cases'!G2:G80,"Pass") | D18: =COUNTIFS('Test Cases'!B2:B80,A18,'Test Cases'!G2:G80,"Fail") | E18: =COUNTIFS('Test Cases'!B2:B80,A18,'Test Cases'!G2:G80,"Not Run")
A19: CORETAX | B19: =COUNTIF('Test Cases'!B2:B80,A19) | C19: =COUNTIFS('Test Cases'!B2:B80,A19,'Test Cases'!G2:G80,"Pass") | D19: =COUNTIFS('Test Cases'!B2:B80,A19,'Test Cases'!G2:G80,"Fail") | E19: =COUNTIFS('Test Cases'!B2:B80,A19,'Test Cases'!G2:G80,"Not Run")
A20: Purchase | B20: =COUNTIF('Test Cases'!B2:B80,A20) | C20: =COUNTIFS('Test Cases'!B2:B80,A20,'Test Cases'!G2:G80,"Pass") | D20: =COUNTIFS('Test Cases'!B2:B80,A20,'Test Cases'!G2:G80,"Fail") | E20: =COUNTIFS('Test Cases'!B2:B80,A20,'Test Cases'!G2:G80,"Not Run")
A21: CRM | B21: =COUNTIF('Test Cases'!B2:B80,A21) | C21: =COUNTIFS('Test Cases'!B2:B80,A21,'Test Cases'!G2:G80,"Pass") | D21: =COUNTIFS('Test Cases'!B2:B80,A21,'Test Cases'!G2:G80,"Fail") | E21: =COUNTIFS('Test Cases'!B2:B80,A21,'Test Cases'!G2:G80,"Not Run")
A22: Project (Fit-out) | B22: =COUNTIF('Test Cases'!B2:B80,A22) | C22: =COUNTIFS('Test Cases'!B2:B80,A22,'Test Cases'!G2:G80,"Pass") | D22: =COUNTIFS('Test Cases'!B2:B80,A22,'Test Cases'!G2:G80,"Fail") | E22: =COUNTIFS('Test Cases'!B2:B80,A22,'Test Cases'!G2:G80,"Not Run")
A23: Documents | B23: =COUNTIF('Test Cases'!B2:B80,A23) | C23: =COUNTIFS('Test Cases'!B2:B80,A23,'Test Cases'!G2:G80,"Pass") | D23: =COUNTIFS('Test Cases'!B2:B80,A23,'Test Cases'!G2:G80,"Fail") | E23: =COUNTIFS('Test Cases'!B2:B80,A23,'Test Cases'!G2:G80,"Not Run")
A24: Fixed Assets | B24: =COUNTIF('Test Cases'!B2:B80,A24) | C24: =COUNTIFS('Test Cases'!B2:B80,A24,'Test Cases'!G2:G80,"Pass") | D24: =COUNTIFS('Test Cases'!B2:B80,A24,'Test Cases'!G2:G80,"Fail") | E24: =COUNTIFS('Test Cases'!B2:B80,A24,'Test Cases'!G2:G80,"Not Run")
A25: Documents CE | B25: =COUNTIF('Test Cases'!B2:B80,A25) | C25: =COUNTIFS('Test Cases'!B2:B80,A25,'Test Cases'!G2:G80,"Pass") | D25: =COUNTIFS('Test Cases'!B2:B80,A25,'Test Cases'!G2:G80,"Fail") | E25: =COUNTIFS('Test Cases'!B2:B80,A25,'Test Cases'!G2:G80,"Not Run")
A26: Owner Portal | B26: =COUNTIF('Test Cases'!B2:B80,A26) | C26: =COUNTIFS('Test Cases'!B2:B80,A26,'Test Cases'!G2:G80,"Pass") | D26: =COUNTIFS('Test Cases'!B2:B80,A26,'Test Cases'!G2:G80,"Fail") | E26: =COUNTIFS('Test Cases'!B2:B80,A26,'Test Cases'!G2:G80,"Not Run")
A27: CAM / Service Charge | B27: =COUNTIF('Test Cases'!B2:B80,A27) | C27: =COUNTIFS('Test Cases'!B2:B80,A27,'Test Cases'!G2:G80,"Pass") | D27: =COUNTIFS('Test Cases'!B2:B80,A27,'Test Cases'!G2:G80,"Fail") | E27: =COUNTIFS('Test Cases'!B2:B80,A27,'Test Cases'!G2:G80,"Not Run")
A28: Rent Escalation | B28: =COUNTIF('Test Cases'!B2:B80,A28) | C28: =COUNTIFS('Test Cases'!B2:B80,A28,'Test Cases'!G2:G80,"Pass") | D28: =COUNTIFS('Test Cases'!B2:B80,A28,'Test Cases'!G2:G80,"Fail") | E28: =COUNTIFS('Test Cases'!B2:B80,A28,'Test Cases'!G2:G80,"Not Run")
A29: KPI Dashboard | B29: =COUNTIF('Test Cases'!B2:B80,A29) | C29: =COUNTIFS('Test Cases'!B2:B80,A29,'Test Cases'!G2:G80,"Pass") | D29: =COUNTIFS('Test Cases'!B2:B80,A29,'Test Cases'!G2:G80,"Fail") | E29: =COUNTIFS('Test Cases'!B2:B80,A29,'Test Cases'!G2:G80,"Not Run")
A30: Dunning | B30: =COUNTIF('Test Cases'!B2:B80,A30) | C30: =COUNTIFS('Test Cases'!B2:B80,A30,'Test Cases'!G2:G80,"Pass") | D30: =COUNTIFS('Test Cases'!B2:B80,A30,'Test Cases'!G2:G80,"Fail") | E30: =COUNTIFS('Test Cases'!B2:B80,A30,'Test Cases'!G2:G80,"Not Run")
A31: Insurance | B31: =COUNTIF('Test Cases'!B2:B80,A31) | C31: =COUNTIFS('Test Cases'!B2:B80,A31,'Test Cases'!G2:G80,"Pass") | D31: =COUNTIFS('Test Cases'!B2:B80,A31,'Test Cases'!G2:G80,"Fail") | E31: =COUNTIFS('Test Cases'!B2:B80,A31,'Test Cases'!G2:G80,"Not Run")
A32: Lease Expiry | B32: =COUNTIF('Test Cases'!B2:B80,A32) | C32: =COUNTIFS('Test Cases'!B2:B80,A32,'Test Cases'!G2:G80,"Pass") | D32: =COUNTIFS('Test Cases'!B2:B80,A32,'Test Cases'!G2:G80,"Fail") | E32: =COUNTIFS('Test Cases'!B2:B80,A32,'Test Cases'!G2:G80,"Not Run")
A33: Vacancy | B33: =COUNTIF('Test Cases'!B2:B80,A33) | C33: =COUNTIFS('Test Cases'!B2:B80,A33,'Test Cases'!G2:G80,"Pass") | D33: =COUNTIFS('Test Cases'!B2:B80,A33,'Test Cases'!G2:G80,"Fail") | E33: =COUNTIFS('Test Cases'!B2:B80,A33,'Test Cases'!G2:G80,"Not Run")
A34: PPM | B34: =COUNTIF('Test Cases'!B2:B80,A34) | C34: =COUNTIFS('Test Cases'!B2:B80,A34,'Test Cases'!G2:G80,"Pass") | D34: =COUNTIFS('Test Cases'!B2:B80,A34,'Test Cases'!G2:G80,"Fail") | E34: =COUNTIFS('Test Cases'!B2:B80,A34,'Test Cases'!G2:G80,"Not Run")
A35: Parking | B35: =COUNTIF('Test Cases'!B2:B80,A35) | C35: =COUNTIFS('Test Cases'!B2:B80,A35,'Test Cases'!G2:G80,"Pass") | D35: =COUNTIFS('Test Cases'!B2:B80,A35,'Test Cases'!G2:G80,"Fail") | E35: =COUNTIFS('Test Cases'!B2:B80,A35,'Test Cases'!G2:G80,"Not Run")
A36: Valuation | B36: =COUNTIF('Test Cases'!B2:B80,A36) | C36: =COUNTIFS('Test Cases'!B2:B80,A36,'Test Cases'!G2:G80,"Pass") | D36: =COUNTIFS('Test Cases'!B2:B80,A36,'Test Cases'!G2:G80,"Fail") | E36: =COUNTIFS('Test Cases'!B2:B80,A36,'Test Cases'!G2:G80,"Not Run")
A37: Access | B37: =COUNTIF('Test Cases'!B2:B80,A37) | C37: =COUNTIFS('Test Cases'!B2:B80,A37,'Test Cases'!G2:G80,"Pass") | D37: =COUNTIFS('Test Cases'!B2:B80,A37,'Test Cases'!G2:G80,"Fail") | E37: =COUNTIFS('Test Cases'!B2:B80,A37,'Test Cases'!G2:G80,"Not Run")
A38: E-Signature | B38: =COUNTIF('Test Cases'!B2:B80,A38) | C38: =COUNTIFS('Test Cases'!B2:B80,A38,'Test Cases'!G2:G80,"Pass") | D38: =COUNTIFS('Test Cases'!B2:B80,A38,'Test Cases'!G2:G80,"Fail") | E38: =COUNTIFS('Test Cases'!B2:B80,A38,'Test Cases'!G2:G80,"Not Run")
A39: End-to-End | B39: =COUNTIF('Test Cases'!B2:B80,A39) | C39: =COUNTIFS('Test Cases'!B2:B80,A39,'Test Cases'!G2:G80,"Pass") | D39: =COUNTIFS('Test Cases'!B2:B80,A39,'Test Cases'!G2:G80,"Fail") | E39: =COUNTIFS('Test Cases'!B2:B80,A39,'Test Cases'!G2:G80,"Not Run")

Sheet Sign-off
A1: UAT SIGN-OFF
A3: Project | B3: Kustomisasi Property Management Odoo 19 (rental_management companions)
A4: Versi Modul | B4: 19.0.1.0.0
A5: Environment | B5: Staging Odoo 19
A6: Tanggal Mulai UAT
A7: Tanggal Selesai UAT
A8: Diuji oleh (Key User)
A9: Disetujui oleh (PM/SME)
A10: Catatan
